{
  "name": "ST-06 Notifier",
  "active": true,
  "nodes": [
    {
      "parameters": {
        "httpMethod": "POST",
        "path": "spaceship-notify",
        "responseMode": "onReceived",
        "options": {}
      },
      "id": "297f39d5",
      "name": "Webhook",
      "type": "n8n-nodes-base.webhook",
      "typeVersion": 2,
      "position": [
        250,
        300
      ],
      "webhookId": "spaceship-notify"
    },
    {
      "parameters": {
        "assignments": {
          "assignments": [
            {
              "id": "a3b96780",
              "name": "title",
              "value": "={{ $json.body?.title    ?? $json.title    ?? 'SpaceShipIO Alert' }}",
              "type": "string"
            },
            {
              "id": "660d1231",
              "name": "message",
              "value": "={{ $json.body?.message  ?? $json.message  ?? '(no message)' }}",
              "type": "string"
            },
            {
              "id": "0210a8d2",
              "name": "severity",
              "value": "={{ $json.body?.severity ?? $json.severity ?? 'info' }}",
              "type": "string"
            }
          ]
        },
        "options": {}
      },
      "id": "778cb1af",
      "name": "Set Defaults",
      "type": "n8n-nodes-base.set",
      "typeVersion": 3.4,
      "position": [
        450,
        300
      ]
    },
    {
      "parameters": {
        "jsCode": "const sev = $input.first().json.severity || 'info';\nconst e = {info:'\\u2139\\uFE0F', warn:'\\u26A0\\uFE0F', error:'\\U0001F6A8'}[sev] || '\\u2139\\uFE0F';\nconst title = $input.first().json.title;\nconst msg   = $input.first().json.message;\nreturn [{json:{text:`${e} <b>${title}</b>\\n${msg}`}}];"
      },
      "id": "9a34d6bd",
      "name": "Format",
      "type": "n8n-nodes-base.code",
      "typeVersion": 2,
      "position": [
        650,
        300
      ]
    },
    {
      "parameters": {
        "method": "POST",
        "url": "https://api.telegram.org/bot8983287190:AAGm8Zc1dC5FfLgtJKc2FfnX_AeplMqL56c/sendMessage",
        "sendBody": true,
        "specifyBody": "json",
        "jsonBody": "={\"chat_id\":\"7603833558\",\"text\":{{ JSON.stringify($json.text) }},\"parse_mode\":\"HTML\"}",
        "options": {}
      },
      "id": "427d2708",
      "name": "Send Telegram",
      "type": "n8n-nodes-base.httpRequest",
      "typeVersion": 4.2,
      "position": [
        850,
        300
      ]
    }
  ],
  "connections": {
    "Webhook": {
      "main": [
        [
          {
            "node": "Set Defaults",
            "type": "main",
            "index": 0
          }
        ]
      ]
    },
    "Set Defaults": {
      "main": [
        [
          {
            "node": "Format",
            "type": "main",
            "index": 0
          }
        ]
      ]
    },
    "Format": {
      "main": [
        [
          {
            "node": "Send Telegram",
            "type": "main",
            "index": 0
          }
        ]
      ]
    },
    "Send Telegram": {
      "main": [
        []
      ]
    }
  },
  "settings": {
    "executionOrder": "v1",
    "errorWorkflow": "UBBtoeMsOM2deZTM"
  }
}